pvway_pgsema/__init__.py
pvway_pgsema/main.py
pvway_pgsema-0.1.0.dist-info/LICENSE
pvway_pgsema-0.1.0.dist-info/METADATA
pvway_pgsema-0.1.0.dist-info/WHEEL
pvway_pgsema-0.1.0.dist-info/RECORD
